matroska_cache/__init__.py
matroska_cache/backends/__init__.py
matroska_cache/backends/base.py
matroska_cache/backends/redis.py
matroska_cache/cache.py
matroska_cache/dep/__init__.py
matroska_cache/dep/base.py
matroska_cache/dep/id.py
matroska_cache/dep/ntag.py
matroska_cache/dep/primary_key.py
matroska_cache/dep/scopes.py
matroska_cache/dep/tag.py
matroska_cache/exc.py
matroska_cache/sa_tools.py
matroska_cache-0.1.3.dist-info/LICENSE
matroska_cache-0.1.3.dist-info/WHEEL
matroska_cache-0.1.3.dist-info/METADATA
matroska_cache-0.1.3.dist-info/RECORD
