Metadata-Version: 2.1
Name: matroska-cache
Version: 0.1.3
Summary: Caching with dependency tracking
Home-page: https://github.com/kolypto/py-matroska_cache
Author: Mark Vartanyan
Author-email: kolypto@gmail.com
Requires-Python: >=3.7,<4.0
Classifier: Programming Language :: Python :: 3
Classifier: Programming Language :: Python :: 3.7
Classifier: Programming Language :: Python :: 3.8
Requires-Dist: redis (>=3.0,<4.0)
Requires-Dist: sqlalchemy (>=1.3,<2.0)
Project-URL: Repository, https://github.com/kolypto/py-matroska_cache
